django_ssh/__init__.py
django_ssh/admin.py
django_ssh/apps.py
django_ssh/forms.py
django_ssh/models.py
django_ssh/urls.py
django_ssh/version.py
django_ssh/views.py
django_ssh/migrations/0001_initial.py
django_ssh/migrations/__init__.py
django_ssh/tests/__init__.py
django_ssh/tests/test_basic.py
django_ssh-0.2.3.dist-info/LICENSE
django_ssh-0.2.3.dist-info/METADATA
django_ssh-0.2.3.dist-info/WHEEL
django_ssh-0.2.3.dist-info/top_level.txt
django_ssh-0.2.3.dist-info/RECORD
